csv2notion_neo/__init__.py
csv2notion_neo/__main__.py
csv2notion_neo/cli.py
csv2notion_neo/cli_args.py
csv2notion_neo/cli_steps.py
csv2notion_neo/local_data.py
csv2notion_neo/notion_client.py
csv2notion_neo/notion_convert.py
csv2notion_neo/notion_convert_map.py
csv2notion_neo/notion_db.py
csv2notion_neo/notion_db_client.py
csv2notion_neo/notion_preparator.py
csv2notion_neo/notion_row_upload_file.py
csv2notion_neo/notion_type_guess.py
csv2notion_neo/notion_uploader.py
csv2notion_neo/utils_ai.py
csv2notion_neo/utils_db.py
csv2notion_neo/utils_exceptions.py
csv2notion_neo/utils_file.py
csv2notion_neo/utils_rand_id.py
csv2notion_neo/utils_static.py
csv2notion_neo/utils_str.py
csv2notion_neo/utils_threading.py
csv2notion_neo/version.py
csv2notion_neo-2.0.2.dist-info/LICENSE
csv2notion_neo-2.0.2.dist-info/METADATA
csv2notion_neo-2.0.2.dist-info/WHEEL
csv2notion_neo-2.0.2.dist-info/entry_points.txt
csv2notion_neo-2.0.2.dist-info/RECORD
