Metadata-Version: 2.3
Name: csv2notion_neo
Version: 2.0.2
Summary: Upload & Merge CSV or JSON Data with Images to Notion Database
License: MIT
Keywords: csv,json,notion,import,merge
Author: Arjun
Author-email: arjunprakash027@gmail.com
Requires-Python: >=3.9,<4.0
Classifier: Development Status :: 5 - Production/Stable
Classifier: Environment :: Console
Classifier: Intended Audience :: End Users/Desktop
Classifier: License :: OSI Approved :: MIT License
Classifier: Natural Language :: English
Classifier: Operating System :: MacOS
Classifier: Operating System :: Microsoft
Classifier: Operating System :: Unix
Classifier: Programming Language :: Python :: 3
Classifier: Programming Language :: Python :: 3.9
Classifier: Programming Language :: Python :: 3.10
Classifier: Programming Language :: Python :: 3.11
Classifier: Programming Language :: Python :: 3.12
Classifier: Programming Language :: Python :: 3.13
Classifier: Topic :: Database
Classifier: Topic :: Internet
Classifier: Topic :: Terminals
Classifier: Topic :: Utilities
Requires-Dist: bs4 (>=0.0.2,<0.0.3)
Requires-Dist: cached-property (>=2.0.1,<3.0.0)
Requires-Dist: commonmark (>=0.9.1,<0.10.0)
Requires-Dist: dictdiffer (>=0.9.0,<0.10.0)
Requires-Dist: emoji (>=2.14.1,<3.0.0)
Requires-Dist: icecream (>=2.1.5,<3.0.0)
Requires-Dist: notion-client (>=2.5.0,<3.0.0)
Requires-Dist: python-dateutil (>=2.9.0.post0,<3.0.0)
Requires-Dist: python-dotenv (>=1.1.1,<2.0.0)
Requires-Dist: python-slugify (>=8.0.4,<9.0.0)
Requires-Dist: ratelimit (>=2.2.1,<3.0.0)
Requires-Dist: requests (>=2.32.4,<3.0.0)
Requires-Dist: tqdm (>=4.67.1,<5.0.0)
Requires-Dist: types-emoji (>=2.1.0.3,<3.0.0.0)
Requires-Dist: types-python-dateutil (>=2.9.0.20250708,<3.0.0.0)
Requires-Dist: types-requests (>=2.32.4.20250611,<3.0.0.0)
Requires-Dist: tzlocal (>=5.3.1,<6.0.0)
Project-URL: Changelog, https://github.com/TheAcharya/csv2notion-neo/blob/master/CHANGELOG.md
Project-URL: Documentation, https://github.com/TheAcharya/csv2notion-neo/blob/master/README.md
Project-URL: Homepage, https://github.com/TheAcharya/csv2notion-neo
Project-URL: Repository, https://github.com/TheAcharya/csv2notion-neo
